ansys/tools/variableinterop/__init__.py
ansys/tools/variableinterop/api_serialization.py
ansys/tools/variableinterop/api_string_to_value_visitor.py
ansys/tools/variableinterop/array_metadata.py
ansys/tools/variableinterop/array_value_conversion.py
ansys/tools/variableinterop/array_values.py
ansys/tools/variableinterop/common_variable_metadata.py
ansys/tools/variableinterop/exceptions.py
ansys/tools/variableinterop/file_array_metadata.py
ansys/tools/variableinterop/file_array_value.py
ansys/tools/variableinterop/file_metadata.py
ansys/tools/variableinterop/file_scope.py
ansys/tools/variableinterop/file_value.py
ansys/tools/variableinterop/from_formatted_string_visitor.py
ansys/tools/variableinterop/isave_context.py
ansys/tools/variableinterop/ivariable_type_pseudovisitor.py
ansys/tools/variableinterop/ivariable_visitor.py
ansys/tools/variableinterop/ivariablemetadata_visitor.py
ansys/tools/variableinterop/non_managing_file_scope.py
ansys/tools/variableinterop/numeric_metadata.py
ansys/tools/variableinterop/py.typed
ansys/tools/variableinterop/scalar_metadata.py
ansys/tools/variableinterop/scalar_value_conversion.py
ansys/tools/variableinterop/scalar_values.py
ansys/tools/variableinterop/strings.properties
ansys/tools/variableinterop/value_from_formatted_string.py
ansys/tools/variableinterop/var_type_array_check.py
ansys/tools/variableinterop/variable_state.py
ansys/tools/variableinterop/variable_type.py
ansys/tools/variableinterop/variable_value.py
ansys/tools/variableinterop/vartype_arrays_and_elements.py
ansys/tools/variableinterop/utils/__init__.py
ansys/tools/variableinterop/utils/array_to_from_string_util.py
ansys/tools/variableinterop/utils/implicit_coercion.py
ansys/tools/variableinterop/utils/locale_utils.py
ansys/tools/variableinterop/utils/string_escaping.py
ansys/tools/variableinterop/utils/variable_type_util.py
pyansys_tools_variableinterop-0.1.2.dist-info/licenses/LICENSE
pyansys_tools_variableinterop-0.1.2.dist-info/WHEEL
pyansys_tools_variableinterop-0.1.2.dist-info/METADATA
pyansys_tools_variableinterop-0.1.2.dist-info/RECORD
