Metadata-Version: 2.4
Name: pyansys-tools-variableinterop
Version: 0.1.2
Summary: Optional variable specifications for interoperability between languages and capabilities.
Author-email: "ANSYS, Inc." <pyansys.core@ansys.com>
Maintainer-email: "ANSYS, Inc." <pyansys.core@ansys.com>
Requires-Python: >=3.10,<4
Classifier: Development Status :: 4 - Beta
Classifier: License :: OSI Approved :: MIT License
Classifier: Operating System :: OS Independent
Classifier: Programming Language :: Python :: 3.10
Classifier: Programming Language :: Python :: 3.11
Classifier: Programming Language :: Python :: 3.12
Classifier: Programming Language :: Python :: 3.13
License-File: LICENSE
Requires-Dist: anyio>=3.5
Requires-Dist: numpy>=1.20.3
Requires-Dist: overrides>=7.4
Requires-Dist: ansys-sphinx-theme[autoapi]==1.6.3 ; extra == "doc"
Requires-Dist: numpydoc==1.10.0 ; extra == "doc"
Requires-Dist: Sphinx==8.2.3 ; extra == "doc"
Requires-Dist: sphinx-copybutton==0.5.2 ; extra == "doc"
Requires-Dist: sphinx-notfound-page==1.1.0 ; extra == "doc"
Requires-Dist: sphinx-gallery==0.20.0 ; extra == "doc"
Requires-Dist: sphinx-design==0.6.1 ; extra == "doc"
Requires-Dist: pytest-sphinx==0.6.3 ; extra == "doc"
Requires-Dist: anyio==4.12.0 ; extra == "tests"
Requires-Dist: numpy==2.2.3 ; extra == "tests"
Requires-Dist: overrides==7.7.0 ; extra == "tests"
Requires-Dist: pytest==9.0.2 ; extra == "tests"
Requires-Dist: pytest-cov==7.0.0 ; extra == "tests"
Requires-Dist: pytest-mock==3.15.1 ; extra == "tests"
Project-URL: Discussions, https://github.com/ansys/pyansys-tools-variableinterop/discussions
Project-URL: Issues, https://github.com/ansys/pyansys-tools-variableinterop/issues
Project-URL: Source, https://github.com/ansys/pyansys-tools-variableinterop
Provides-Extra: doc
Provides-Extra: tests
